.gitignore
LICENSE
MANIFEST.in
README.md
setup.py
demcoreg/__init__.py
demcoreg/anomaly_maps.py
demcoreg/apply_dem_translation.py
demcoreg/apply_trans_all.sh
demcoreg/compute_diff.py
demcoreg/compute_diff_all.sh
demcoreg/conus_site_poly.py
demcoreg/coreglib.py
demcoreg/dem_align.py
demcoreg/dem_align_parallel.pbs
demcoreg/dem_align_post.ipynb
demcoreg/dem_align_post.py
demcoreg/dem_align_wip.py
demcoreg/dem_coreg.sh
demcoreg/dem_coreg_all.sh
demcoreg/dem_mask.py
demcoreg/filter_glas.py
demcoreg/get_bareground.sh
demcoreg/get_glcf.sh
demcoreg/get_hydro.sh
demcoreg/get_natearth.sh
demcoreg/get_nlcd.sh
demcoreg/get_refdem.sh
demcoreg/get_rgi.sh
demcoreg/glas_analysis.py
demcoreg/glas_proc.py
demcoreg/modis_grid.py
demcoreg/pc_align_error_analysis.py
demcoreg/pc_align_wrapper.sh
demcoreg/robust_stats.py
demcoreg/sample_raster_at_pts.py
demcoreg/vol_stats.py
demcoreg.egg-info/PKG-INFO
demcoreg.egg-info/SOURCES.txt
demcoreg.egg-info/dependency_links.txt
demcoreg.egg-info/requires.txt
demcoreg.egg-info/top_level.txt
docs/20081123_0446_1735796131_1735796132_40m-DEM_hma_nasadem_hgt_lt5m_err_nuth_x+26.19_y+182.36_z-65.52_align_sm.jpg
docs/20151227_0803_10200100499B7700_10200100496E3000-DEM_32m_glas_sm.jpg
docs/Makefile
docs/Sheanetal_2016_ISPRS.pdf
docs/beginners_doc.md
docs/conf.py
docs/coreglib.rst
docs/dem_mask_example_sm.jpg
docs/index.rst
docs/intro.rst
docs/nuth_sample.jpg
docs/readme.md
docs/requirements.txt
docs/tools.rst
docs/tools/apply_dem_translation.rst
docs/tools/compute_dz.rst
docs/tools/dem_align.rst
docs/tools/dem_coreg.rst
docs/tools/dem_coreg_all.rst
docs/tools/dem_mask.rst
docs/tools/glas_proc.rst
docs/tools/pc_align_wrapper.rst
docs/tools/robust_stats.rst
docs/tools/vol_stats.rst