Metadata-Version: 2.1
Name: demcoreg
Version: 1.1.2
Summary: Utilities for DEM co-registration
Home-page: https://github.com/dshean/demcoreg
Author: David Shean
Author-email: dshean@gmail.com
License: MIT
License-File: LICENSE
Requires-Dist: numpy
Requires-Dist: gdal
Requires-Dist: pygeotools
Requires-Dist: wget
